deamons/__init__.py
deamons-1.0.0.dist-info/LICENSE
deamons-1.0.0.dist-info/METADATA
deamons-1.0.0.dist-info/WHEEL
deamons-1.0.0.dist-info/top_level.txt
deamons-1.0.0.dist-info/RECORD
